beans/BeansTable.py
beans/PlainConnector.py
beans/__init__.py
beans/beans.py
beans/usage.md
beans/testing/__init__.py
beans/testing/out name 1
beans/testing/testing.py
beans_cli-1.0.1.dist-info/METADATA
beans_cli-1.0.1.dist-info/WHEEL
beans_cli-1.0.1.dist-info/entry_points.txt
beans_cli-1.0.1.dist-info/licenses/LICENSE
beans_cli-1.0.1.dist-info/RECORD
