Metadata-Version: 2.4
Name: beans-cli
Version: 1.0.1
Summary: BEANS python scripts, and helper classes
Project-URL: Homepage, https://gitlab.com/beans-code/beans-cli
Project-URL: Issues, https://gitlab.com/beans-code/beans-cli/-/issues/
Author: Arkadiusz Hypki
License-Expression: MIT
License-File: LICENSE
Classifier: Operating System :: OS Independent
Classifier: Programming Language :: Python :: 3
Requires-Python: >=3.9
